libpyles/__init__.py
libpyles/libpyles.py
libpyles-1.0.9.dist-info/METADATA
libpyles-1.0.9.dist-info/WHEEL
libpyles-1.0.9.dist-info/top_level.txt
libpyles-1.0.9.dist-info/RECORD
