Metadata-Version: 2.1
Name: libpyles
Version: 1.0.9
Summary: Pacote para mnipulação de arquivos
Author: PedroVitor
Author-email: pedro.passos@ufpi.edu.br
Keywords: python,files,Pyl3s,Pyl3sLib, libpyles
Requires-Dist: PyPDF2
Requires-Dist: fpdf
